py3crdt/__init__.py
py3crdt/gcounter.py
py3crdt/gset.py
py3crdt/lww.py
py3crdt/node.py
py3crdt/orset.py
py3crdt/pncounter.py
py3crdt/sequence.py
py3crdt/twopset.py
src/__init__.py
src/gcounter.py
src/gset.py
src/lww.py
src/node.py
src/orset.py
src/pncounter.py
src/sequence.py
src/twopset.py
src/__pycache__/__init__.cpython-37.pyc
src/__pycache__/gcounter.cpython-37.pyc
src/__pycache__/gset.cpython-37.pyc
src/__pycache__/lww.cpython-37.pyc
src/__pycache__/node.cpython-37.pyc
src/__pycache__/orset.cpython-37.pyc
src/__pycache__/pncounter.cpython-37.pyc
src/__pycache__/sequence.cpython-37.pyc
src/__pycache__/twopset.cpython-37.pyc
tests/__init__.py
tests/set_sys_path.py
tests/test_gcounter.py
tests/test_gset.py
tests/test_lww.py
tests/test_orset.py
tests/test_pncounter.py
tests/test_sequence.py
tests/test_twopset.py
tests/__pycache__/set_sys_path.cpython-37.pyc
tests/__pycache__/test_gcounter.cpython-37.pyc
tests/__pycache__/test_gset.cpython-37.pyc
tests/__pycache__/test_lww.cpython-37.pyc
tests/__pycache__/test_orset.cpython-37.pyc
tests/__pycache__/test_pncounter.cpython-37.pyc
tests/__pycache__/test_sequence.cpython-37.pyc
tests/__pycache__/test_twopset.cpython-37.pyc
python3_crdt-1.0.3.dist-info/LICENSE
python3_crdt-1.0.3.dist-info/METADATA
python3_crdt-1.0.3.dist-info/WHEEL
python3_crdt-1.0.3.dist-info/top_level.txt
python3_crdt-1.0.3.dist-info/RECORD
