Metadata-Version: 2.1
Name: python3-crdt
Version: 1.0.3
Summary: A python library for CRDTs (Conflict-free Replicated Data types)
Home-page: https://github.com/geetesh-gupta/python3-crdt
Author: Geetesh Gupta
Author-email: ggguitarg31@gmail.com
License: UNKNOWN
Platform: UNKNOWN
Classifier: Programming Language :: Python :: 3
Classifier: License :: OSI Approved :: MIT License
Classifier: Operating System :: OS Independent
Classifier: Intended Audience :: Science/Research
Classifier: Intended Audience :: Developers
Classifier: Topic :: Software Development :: Libraries :: Python Modules
